{"type": "Feature", "id": 12518459, "geometry": {"type": "Point", "coordinates": [32.724499, 50.469002]}, "properties": {"woe:id": 12518459, "woe:parent_id": 937005, "woe:name": "Varva Airport", "woe:placetype": 14, "woe:placetype_name": "Airport", "woe:lang": "ENG", "iso:country": "UA", "meta:provider": ["geoplanet:7.3.1", "geoplanet:7.3.2", "geoplanet:7.4.0", "geoplanet:7.4.1", "geoplanet:7.5.1", "geoplanet:7.5.2", "geoplanet:7.6.0", "geoplanet:7.8.1", "geoplanet:7.9.0", "geoplanet:7.10.0", "geoplanet:8.0.0", "woeplanet:8.0.0"], "meta:indexed": "2020-08-20T20:49:14.880290", "meta:updated": "2020-10-14T11:51:20.167599", "woe:hierarchy": {"continent": 24865675, "country": 23424976, "town": 0, "planet": 1, "county": 0, "suburb": 0, "state": 2347535, "region": 0, "localadmin": 0}, "woe:timezone_id": 56043618, "woe:hash": "u8zr0et70pg5", "woe:centroid": [32.724499, 50.469002], "geom:latitude": 50.469002, "geom:longitude": 32.724499, "geom:hash": "u8zr0et70pg5", "woe:latitude": 50.469002, "geom:centroid": [32.724499, 50.469002], "woe:longitude": 32.724499, "woe:repo": "woeplanet-airport-ua", "geom:area": 0.0, "woe:scale": 19}}