{"type": "Feature", "id": 12518481, "geometry": {"type": "Point", "coordinates": [38.380901, 48.481701]}, "properties": {"woe:id": 12518481, "woe:parent_id": 915864, "woe:name": "Vorosilova Airport", "woe:placetype": 14, "woe:placetype_name": "Airport", "woe:lang": "ENG", "iso:country": "UA", "meta:provider": ["geoplanet:7.3.1", "geoplanet:7.3.2", "geoplanet:7.4.0", "geoplanet:7.4.1", "geoplanet:7.5.1", "geoplanet:7.5.2", "geoplanet:7.6.0", "geoplanet:7.8.1", "geoplanet:7.9.0", "geoplanet:7.10.0", "geoplanet:8.0.0", "woeplanet:8.0.0"], "meta:indexed": "2020-08-20T20:49:14.896324", "meta:updated": "2020-10-14T11:51:20.204607", "woe:hierarchy": {"continent": 24865675, "country": 23424976, "town": 0, "planet": 1, "county": 0, "suburb": 0, "state": 2347546, "region": 0, "localadmin": 0}, "woe:timezone_id": 56043618, "woe:hash": "ube7c3u47u45", "woe:centroid": [38.380901, 48.481701], "geom:latitude": 48.481701, "geom:longitude": 38.380901, "geom:hash": "ube7c3u47u45", "woe:latitude": 48.481701, "geom:centroid": [38.380901, 48.481701], "woe:longitude": 38.380901, "woe:repo": "woeplanet-airport-ua", "geom:area": 0.0, "woe:scale": 19}}