{"type": "Feature", "id": 12518397, "geometry": {"type": "Point", "coordinates": [34.0597, 51.855]}, "properties": {"woe:id": 12518397, "woe:parent_id": 935572, "woe:name": "Pustogorod Airport", "woe:placetype": 14, "woe:placetype_name": "Airport", "woe:lang": "ENG", "iso:country": "UA", "meta:provider": ["geoplanet:7.3.1", "geoplanet:7.3.2", "geoplanet:7.4.0", "geoplanet:7.4.1", "geoplanet:7.5.1", "geoplanet:7.5.2", "geoplanet:7.6.0", "geoplanet:7.8.1", "geoplanet:7.9.0", "geoplanet:7.10.0", "geoplanet:8.0.0", "woeplanet:8.0.0"], "meta:indexed": "2020-08-20T20:49:14.826639", "meta:updated": "2020-10-14T11:51:20.059297", "woe:hierarchy": {"continent": 24865675, "country": 23424976, "town": 0, "planet": 1, "county": 0, "suburb": 0, "state": 2347552, "region": 0, "localadmin": 0}, "woe:timezone_id": 56043618, "woe:hash": "uc0nzpct2895", "woe:centroid": [34.0597, 51.855], "geom:latitude": 51.855, "geom:longitude": 34.0597, "geom:hash": "uc0nzpct2895", "woe:latitude": 51.855, "geom:centroid": [34.0597, 51.855], "woe:longitude": 34.0597, "woe:repo": "woeplanet-airport-ua", "geom:area": 0.0, "woe:scale": 19}}