{"type": "Feature", "id": 12524011, "properties": {"woe:id": 12524011, "woe:parent_id": 923969, "woe:name": "Kramatorsk Airport", "woe:placetype": 14, "woe:placetype_name": "Airport", "woe:lang": "ENG", "iso:country": "UA", "meta:provider": ["geoplanet:7.3.1", "geoplanet:7.3.2", "geoplanet:7.4.0", "geoplanet:7.4.1", "geoplanet:7.5.1", "geoplanet:7.5.2", "geoplanet:7.6.0", "geoplanet:7.8.1", "geoplanet:7.9.0", "geoplanet:7.10.0", "geoplanet:8.0.0", "woeplanet:8.0.0"], "meta:indexed": "2020-08-20T20:49:14.921343", "woe:alias_ENG_V": ["KRQ Airport", "KRQ"], "meta:updated": "2020-08-22T02:50:53.017591", "woe:hierarchy": {"continent": 24865675, "country": 23424976, "town": 0, "planet": 1, "county": 0, "suburb": 0, "state": 2347538, "region": 0, "localadmin": 0}, "woe:timezone_id": 56043618, "woe:hash": "ubdtpuxeke7x", "woe:centroid": [37.616699, 48.716702], "geom:latitude": 48.716702, "geom:longitude": 37.616699, "geom:hash": "ubdtpuxeke7x", "woe:latitude": 48.716702, "geom:centroid": [37.616699, 48.716702], "woe:longitude": 37.616699, "woe:repo": "woeplanet-airport-ua"}, "geometry": {"coordinates": [37.616699, 48.716702], "type": "Point"}}