{"type": "Feature", "id": 12518467, "geometry": {"type": "Point", "coordinates": [28.5632, 49.231602]}, "properties": {"woe:id": 12518467, "woe:parent_id": 937883, "woe:name": "Vinnitsa Airport", "woe:placetype": 14, "woe:placetype_name": "Airport", "woe:lang": "ENG", "iso:country": "UA", "meta:provider": ["geoplanet:7.3.1", "geoplanet:7.3.2", "geoplanet:7.4.0", "geoplanet:7.4.1", "geoplanet:7.5.1", "geoplanet:7.5.2", "geoplanet:7.6.0", "geoplanet:7.8.1", "geoplanet:7.9.0", "geoplanet:7.10.0", "geoplanet:8.0.0", "woeplanet:8.0.0"], "meta:indexed": "2020-08-20T20:49:14.885429", "woe:alias_ENG_V": ["VIN Airport", "VIN"], "meta:updated": "2020-10-14T11:51:20.206185", "woe:hierarchy": {"continent": 24865675, "country": 23424976, "town": 0, "planet": 1, "county": 0, "suburb": 0, "state": 2347554, "region": 0, "localadmin": 0}, "woe:timezone_id": 56043618, "woe:hash": "u8u21fr4fgc9", "woe:centroid": [28.5632, 49.231602], "geom:latitude": 49.231602, "geom:longitude": 28.5632, "geom:hash": "u8u21fr4fgc9", "woe:latitude": 49.231602, "geom:centroid": [28.5632, 49.231602], "woe:longitude": 28.5632, "woe:repo": "woeplanet-airport-ua", "geom:area": 0.0, "woe:scale": 19}}