{"type": "Feature", "id": 12518444, "properties": {"woe:id": 12518444, "woe:parent_id": 935200, "woe:name": "Sumy Northwest Airport", "woe:placetype": 14, "woe:placetype_name": "Airport", "woe:lang": "ENG", "iso:country": "UA", "meta:provider": ["geoplanet:7.3.1", "geoplanet:7.3.2", "geoplanet:7.4.0", "geoplanet:7.4.1", "geoplanet:7.5.1", "geoplanet:7.5.2", "geoplanet:7.6.0", "geoplanet:7.8.1", "geoplanet:7.9.0", "geoplanet:7.10.0", "geoplanet:8.0.0", "woeplanet:8.0.0"], "meta:indexed": "2020-08-20T20:49:14.868783", "meta:updated": "2020-08-22T02:50:52.992623", "woe:hierarchy": {"continent": 24865675, "country": 23424976, "town": 0, "planet": 1, "county": 0, "suburb": 0, "state": 2347552, "region": 0, "localadmin": 0}, "woe:timezone_id": 56043618, "woe:hash": "uc09vqdgk77j", "woe:centroid": [34.687801, 50.968899], "geom:latitude": 50.968899, "geom:longitude": 34.687801, "geom:hash": "uc09vqdgk77j", "woe:latitude": 50.968899, "geom:centroid": [34.687801, 50.968899], "woe:longitude": 34.687801, "woe:repo": "woeplanet-airport-ua"}, "geometry": {"coordinates": [34.687801, 50.968899], "type": "Point"}}