{"type": "Feature", "id": 12518284, "geometry": {"type": "Point", "coordinates": [36.0383, 49.978001]}, "properties": {"woe:id": 12518284, "woe:parent_id": 934555, "woe:name": "Kharkov-Lyubotin Airport", "woe:placetype": 14, "woe:placetype_name": "Airport", "woe:lang": "ENG", "iso:country": "UA", "meta:provider": ["geoplanet:7.3.1", "geoplanet:7.3.2", "geoplanet:7.4.0", "geoplanet:7.4.1", "geoplanet:7.5.1", "geoplanet:7.5.2", "geoplanet:7.6.0", "geoplanet:7.8.1", "geoplanet:7.9.0", "geoplanet:7.10.0", "geoplanet:8.0.0", "woeplanet:8.0.0"], "meta:indexed": "2020-08-20T20:49:14.717123", "meta:updated": "2020-10-14T11:51:20.115140", "woe:hierarchy": {"continent": 24865675, "country": 23424976, "town": 0, "planet": 1, "county": 0, "suburb": 0, "state": 2347540, "region": 0, "localadmin": 0}, "woe:timezone_id": 56043618, "woe:hash": "ubcsk44qcq8h", "woe:centroid": [36.0383, 49.978001], "geom:latitude": 49.978001, "geom:longitude": 36.0383, "geom:hash": "ubcsk44qcq8h", "woe:latitude": 49.978001, "geom:centroid": [36.0383, 49.978001], "woe:longitude": 36.0383, "woe:repo": "woeplanet-airport-ua", "geom:area": 0.0, "woe:scale": 19}}