{"type": "Feature", "id": 12518406, "properties": {"woe:id": 12518406, "woe:parent_id": 932508, "woe:name": "Rotmistrovka Airport", "woe:placetype": 14, "woe:placetype_name": "Airport", "woe:lang": "ENG", "iso:country": "UA", "meta:provider": ["geoplanet:7.3.1", "geoplanet:7.3.2", "geoplanet:7.4.0", "geoplanet:7.4.1", "geoplanet:7.5.1", "geoplanet:7.5.2", "geoplanet:7.6.0", "geoplanet:7.8.1", "geoplanet:7.9.0", "geoplanet:7.10.0", "geoplanet:8.0.0", "woeplanet:8.0.0"], "meta:indexed": "2020-08-20T20:49:14.835105", "meta:updated": "2020-08-22T02:50:52.980023", "woe:hierarchy": {"continent": 24865675, "country": 23424976, "town": 0, "planet": 1, "county": 0, "suburb": 0, "state": 2347534, "region": 0, "localadmin": 0}, "woe:timezone_id": 56043618, "woe:hash": "u8wx2zd7fzyj", "woe:centroid": [31.6768, 49.128799], "geom:latitude": 49.128799, "geom:longitude": 31.6768, "geom:hash": "u8wx2zd7fzyj", "woe:latitude": 49.128799, "geom:centroid": [31.6768, 49.128799], "woe:longitude": 31.6768, "woe:repo": "woeplanet-airport-ua"}, "geometry": {"coordinates": [31.6768, 49.128799], "type": "Point"}}