{"type": "Feature", "id": 12518199, "properties": {"woe:id": 12518199, "woe:parent_id": 916648, "woe:name": "Berdichev Airport", "woe:placetype": 14, "woe:placetype_name": "Airport", "woe:lang": "ENG", "iso:country": "UA", "meta:provider": ["geoplanet:7.3.1", "geoplanet:7.3.2", "geoplanet:7.4.0", "geoplanet:7.4.1", "geoplanet:7.5.1", "geoplanet:7.5.2", "geoplanet:7.6.0", "geoplanet:7.8.1", "geoplanet:7.9.0", "geoplanet:7.10.0", "geoplanet:8.0.0", "woeplanet:8.0.0"], "meta:indexed": "2020-08-20T20:49:14.635056", "meta:updated": "2020-08-22T02:50:52.902631", "woe:hierarchy": {"continent": 24865675, "country": 23424976, "town": 0, "planet": 1, "county": 0, "suburb": 0, "state": 2347558, "region": 0, "localadmin": 0}, "woe:timezone_id": 56043618, "woe:hash": "u8u7b8ckmu14", "woe:centroid": [28.5005, 49.882801], "geom:latitude": 49.882801, "geom:longitude": 28.5005, "geom:hash": "u8u7b8ckmu14", "woe:latitude": 49.882801, "geom:centroid": [28.5005, 49.882801], "woe:longitude": 28.5005, "woe:repo": "woeplanet-airport-ua"}, "geometry": {"coordinates": [28.5005, 49.882801], "type": "Point"}}