{"type": "Feature", "id": 12518328, "geometry": {"type": "Point", "coordinates": [35.587799, 47.743401]}, "properties": {"woe:id": 12518328, "woe:parent_id": 921739, "woe:name": "Kuscheva Airport", "woe:placetype": 14, "woe:placetype_name": "Airport", "woe:lang": "ENG", "iso:country": "UA", "meta:provider": ["geoplanet:7.3.1", "geoplanet:7.3.2", "geoplanet:7.4.0", "geoplanet:7.4.1", "geoplanet:7.5.1", "geoplanet:7.5.2", "geoplanet:7.6.0", "geoplanet:7.8.1", "geoplanet:7.9.0", "geoplanet:7.10.0", "geoplanet:8.0.0", "woeplanet:8.0.0"], "meta:indexed": "2020-08-20T20:49:14.759541", "meta:updated": "2020-10-14T11:51:20.074824", "woe:hierarchy": {"continent": 24865675, "country": 23424976, "town": 0, "planet": 1, "county": 0, "suburb": 0, "state": 2347557, "region": 0, "localadmin": 0}, "woe:timezone_id": 56043616, "woe:hash": "ub3r9g6jrz42", "woe:centroid": [35.587799, 47.743401], "geom:latitude": 47.743401, "geom:longitude": 35.587799, "geom:hash": "ub3r9g6jrz42", "woe:latitude": 47.743401, "geom:centroid": [35.587799, 47.743401], "woe:longitude": 35.587799, "woe:repo": "woeplanet-airport-ua", "geom:area": 0.0, "woe:scale": 19}}