{"type": "Feature", "id": 12518371, "properties": {"woe:id": 12518371, "woe:parent_id": 919124, "woe:name": "Novosofiyevka Airport", "woe:placetype": 14, "woe:placetype_name": "Airport", "woe:lang": "ENG", "iso:country": "UA", "meta:provider": ["geoplanet:7.3.1", "geoplanet:7.3.2", "geoplanet:7.4.0", "geoplanet:7.4.1", "geoplanet:7.5.1", "geoplanet:7.5.2", "geoplanet:7.6.0", "geoplanet:7.8.1", "geoplanet:7.9.0", "geoplanet:7.10.0", "geoplanet:8.0.0", "woeplanet:8.0.0"], "meta:indexed": "2020-08-20T20:49:14.801479", "meta:updated": "2020-08-22T02:50:52.967375", "woe:hierarchy": {"continent": 24865675, "country": 23424976, "town": 0, "planet": 1, "county": 0, "suburb": 0, "state": 2347541, "region": 0, "localadmin": 0}, "woe:timezone_id": 56043618, "woe:hash": "u8pnekq0kq5k", "woe:centroid": [32.494999, 46.166], "geom:latitude": 46.166, "geom:longitude": 32.494999, "geom:hash": "u8pnekq0kq5k", "woe:latitude": 46.166, "geom:centroid": [32.494999, 46.166], "woe:longitude": 32.494999, "woe:repo": "woeplanet-airport-ua"}, "geometry": {"coordinates": [32.494999, 46.166], "type": "Point"}}