{"type": "Feature", "id": 12518386, "properties": {"woe:id": 12518386, "woe:parent_id": 931204, "woe:name": "Podvolochisk Airport", "woe:placetype": 14, "woe:placetype_name": "Airport", "woe:lang": "ENG", "iso:country": "UA", "meta:provider": ["geoplanet:7.3.1", "geoplanet:7.3.2", "geoplanet:7.4.0", "geoplanet:7.4.1", "geoplanet:7.5.1", "geoplanet:7.5.2", "geoplanet:7.6.0", "geoplanet:7.8.1", "geoplanet:7.9.0", "geoplanet:7.10.0", "geoplanet:8.0.0", "woeplanet:8.0.0"], "meta:indexed": "2020-08-20T20:49:14.815950", "meta:updated": "2020-08-22T02:50:52.972004", "woe:hierarchy": {"continent": 24865675, "country": 23424976, "town": 0, "planet": 1, "county": 0, "suburb": 0, "state": 2347553, "region": 0, "localadmin": 0}, "woe:timezone_id": 56043618, "woe:hash": "u8f9bf68qt6n", "woe:centroid": [26.052299, 49.538799], "geom:latitude": 49.538799, "geom:longitude": 26.052299, "geom:hash": "u8f9bf68qt6n", "woe:latitude": 49.538799, "geom:centroid": [26.052299, 49.538799], "woe:longitude": 26.052299, "woe:repo": "woeplanet-airport-ua"}, "geometry": {"coordinates": [26.052299, 49.538799], "type": "Point"}}