{"type": "Feature", "id": 12518294, "geometry": {"type": "Point", "coordinates": [32.167599, 48.3535]}, "properties": {"woe:id": 12518294, "woe:parent_id": 938686, "woe:name": "Kirovograd South Airport", "woe:placetype": 14, "woe:placetype_name": "Airport", "woe:lang": "ENG", "iso:country": "UA", "meta:provider": ["geoplanet:7.3.1", "geoplanet:7.3.2", "geoplanet:7.4.0", "geoplanet:7.4.1", "geoplanet:7.5.1", "geoplanet:7.5.2", "geoplanet:7.6.0", "geoplanet:7.8.1", "geoplanet:7.9.0", "geoplanet:7.10.0", "geoplanet:8.0.0", "woeplanet:8.0.0"], "meta:indexed": "2020-08-20T20:49:14.726830", "meta:updated": "2020-10-14T11:51:20.120794", "woe:hierarchy": {"continent": 24865675, "country": 23424976, "town": 0, "planet": 1, "county": 0, "suburb": 0, "state": 2347543, "region": 0, "localadmin": 0}, "woe:timezone_id": 56043618, "woe:hash": "u8wg5frxx3sq", "woe:centroid": [32.167599, 48.3535], "geom:latitude": 48.3535, "geom:longitude": 32.167599, "geom:hash": "u8wg5frxx3sq", "woe:latitude": 48.3535, "geom:centroid": [32.167599, 48.3535], "woe:longitude": 32.167599, "woe:repo": "woeplanet-airport-ua", "geom:area": 0.0, "woe:scale": 19}}